LICENSE
MANIFEST.in
README.md
camazotz.py
setup.py
camazotz.egg-info/PKG-INFO
camazotz.egg-info/SOURCES.txt
camazotz.egg-info/dependency_links.txt
camazotz.egg-info/entry_points.txt
camazotz.egg-info/top_level.txt