Metadata-Version: 1.0
Name: camazotz
Version: 2017.3.20.1950
Summary: template Python program
Home-page: https://github.com/wdbm/camazotz
Author: Will Breaden Madden
Author-email: wbm@protonmail.ch
License: GPLv3
Platform: UNKNOWN
